kioto/__init__.py
kioto/channels/__init__.py
kioto/channels/api.py
kioto/channels/error.py
kioto/channels/impl.py
kioto/futures/__init__.py
kioto/futures/api.py
kioto/futures/impl.py
kioto/internal/__init__.py
kioto/internal/buffer.py
kioto/internal/queue.py
kioto/sink/__init__.py
kioto/sink/api.py
kioto/sink/impl.py
kioto/streams/__init__.py
kioto/streams/api.py
kioto/streams/impl.py
kioto/sync/__init__.py
kioto/sync/api.py
kioto/sync/impl.py
kioto/time/__init__.py
kioto/time/api.py
kioto/time/impl.py
kioto-0.1.13.dist-info/METADATA
kioto-0.1.13.dist-info/WHEEL
kioto-0.1.13.dist-info/licenses/LICENSE
kioto-0.1.13.dist-info/RECORD
