Metadata-Version: 2.4
Name: kioto
Version: 0.1.13
Summary: Async utilities library inspired by Tokio
Author-email: Brandon Ogle <oglebrandon@gmail.com>
License-File: LICENSE
Requires-Python: >=3.8
Requires-Dist: aiofiles==24.1.0
Requires-Dist: ruff>=0.7.1
Provides-Extra: dev
Requires-Dist: coverage[toml]==7.3.2; extra == 'dev'
Requires-Dist: mypy; extra == 'dev'
Requires-Dist: pytest; extra == 'dev'
Requires-Dist: pytest-asyncio; extra == 'dev'
Requires-Dist: pytest-cov==5.0.0; extra == 'dev'
Requires-Dist: ruff; extra == 'dev'
